pmisc/__init__.py
pmisc/ctx.py
pmisc/dicts.py
pmisc/file.py
pmisc/member.py
pmisc/misc.py
pmisc/number.py
pmisc/pkgdata.py
pmisc/rst.py
pmisc/strings.py
pmisc/test.py
pmisc-1.5.12.dist-info/AUTHORS.rst
pmisc-1.5.12.dist-info/LICENSE
pmisc-1.5.12.dist-info/METADATA
pmisc-1.5.12.dist-info/WHEEL
pmisc-1.5.12.dist-info/top_level.txt
pmisc-1.5.12.dist-info/RECORD
