Metadata-Version: 2.1
Name: pmisc
Version: 1.5.12
Summary: UNKNOWN
Home-page: http://github.com/pmacosta/pmisc/
Author: Pablo Acosta-Serafini
Author-email: pmasdev@gmail.com
License: MIT
Platform: any
Classifier: Programming Language :: Python :: 3.5
Classifier: Programming Language :: Python :: 3.6
Classifier: Programming Language :: Python :: 3.7
Classifier: Programming Language :: Python :: 3.8
Classifier: Development Status :: 5 - Production/Stable
Classifier: Natural Language :: English
Classifier: Environment :: Console
Classifier: Intended Audience :: Developers
Classifier: License :: OSI Approved :: MIT License
Classifier: Operating System :: OS Independent
Classifier: Topic :: Software Development :: Libraries :: Python Modules
Requires-Dist: decorator (>=4.4.0)
Requires-Dist: funcsigs (>=1.0.2)
Requires-Dist: pytest (>=4.3.1)
